common_hooks/__init__.py
common_hooks/core.py
common_hooks/conditions/__init__.py
common_hooks/conditions/condition.py
common_hooks/conditions/http_condition.py
common_hooks/fastapi/__init__.py
common_hooks/fastapi/hook.py
common_hooks/httpx/__init__.py
common_hooks/httpx/hook.py
common_hooks-0.0.1.dist-info/METADATA
common_hooks-0.0.1.dist-info/WHEEL
common_hooks-0.0.1.dist-info/top_level.txt
common_hooks-0.0.1.dist-info/RECORD
