Metadata-Version: 2.1
Name: common-hooks
Version: 0.0.1
Summary: A simple way to create hooks (callbacks) to common packages and functions.
Author-email: Fabian Peschke <fabian-peschke@web.de>
Project-URL: Homepage, https://github.com/Fadope1/common-hooks
Keywords: common-hooks,callbacks,python
Classifier: Programming Language :: Python :: 3
Classifier: License :: OSI Approved :: MIT License
Classifier: Operating System :: OS Independent
Requires-Python: >=3.11
Provides-Extra: httpx
Requires-Dist: httpx; extra == "httpx"
Provides-Extra: fastapi
Requires-Dist: fastapi; extra == "fastapi"
Provides-Extra: all
Requires-Dist: httpx; extra == "all"
Requires-Dist: fastapi; extra == "all"
